{
  "MetaData": {
    "Schema": {
      "ManagerName": "AddonSchemaManager",
      "UId": "94ab9eab-e6f1-422d-9f89-2b6c27cd1b03",
      "A2": "UsrRealtyFreedomUIBusinessRule",
      "A5": "3f9d5f54-79ef-4b38-a050-0c0ed03bfa16",
      "B1": [],
      "B2": [],
      "B3": [],
      "B6": "84bd174e-9f64-47e7-bcad-1a666e4604cf",
      "B8": "8.1.0.6827",
      "AD1": "158a7f33-a19c-408f-8af2-aa95bb4e0d0c",
      "AD2": "EntitySchemaManager",
      "AD3": "BusinessRule",
      "AD5": "3a2d6f51-1bfc-4c17-aacb-b53de4866b7c",
      "AD4": {
        "JI0": "Terrasoft.Core.BusinessRules.BusinessRules",
        "BRS1": [
          {
            "JI0": "Terrasoft.Core.BusinessRules.BusinessRule",
            "UId": "3d9c5d93-435c-3281-4f6c-d335aab6f830",
            "BR1": [
              {
                "JI0": "Terrasoft.Core.BusinessRules.Models.BusinessRuleCase",
                "UId": "f9b742ee-0310-8f6e-3c2b-64864347de88",
                "BRC1": {
                  "JI0": "Terrasoft.Core.BusinessRules.Models.Conditions.BusinessRuleGroupCondition",
                  "UId": "db59dd2a-c4bf-7c06-6bf2-db667472ce8c",
                  "BGC1": 1,
                  "BGC2": []
                },
                "BRC2": [
                  {
                    "JI0": "Terrasoft.Core.BusinessRules.Models.Actions.BusinessRuleActionSetFilter",
                    "UId": "8b3b3211-65b1-7e56-277d-e11700cf3e34",
                    "BRA2": {
                      "JI0": "Terrasoft.Core.BusinessRules.Models.Expressions.BusinessRuleAttributeExpression",
                      "UId": "a4749f9a-bb5c-e847-bf22-1cb91b66a811",
                      "BRX1": "UsrManager"
                    },
                    "BRA3": {
                      "JI0": "Terrasoft.Core.BusinessRules.Models.Expressions.BusinessRuleValueExpression",
                      "UId": "3e5388af-0cc8-4044-5f5a-9d44ef04c194",
                      "BVE1": "{\"items\":{\"90c36e04-90bf-4ec4-bd3c-842216e439e8\":{\"filterType\":4,\"comparisonType\":3,\"isEnabled\":true,\"trimDateTimeParameterToDate\":false,\"leftExpression\":{\"expressionType\":0,\"columnPath\":\"Type\"},\"isAggregative\":false,\"dataValueType\":10,\"referenceSchemaName\":\"ContactType\",\"rightExpressions\":[{\"expressionType\":2,\"parameter\":{\"dataValueType\":10,\"value\":{\"Name\":\"Employee\",\"Id\":\"60733efc-f36b-1410-a883-16d83cab0980\",\"value\":\"60733efc-f36b-1410-a883-16d83cab0980\",\"displayValue\":\"Employee\"}}}]}},\"logicalOperation\":0,\"isEnabled\":true,\"filterType\":6,\"rootSchemaName\":\"Contact\"}"
                    }
                  }
                ]
              }
            ],
            "BR2": [
              {
                "JI0": "Terrasoft.Core.BusinessRules.Models.Trigger",
                "UId": "d0dc6227-2ba0-c8e7-5aea-2f7424cc35c4",
                "BRT1": "null",
                "BRT3": "null",
                "BRT2": 2
              }
            ],
            "BR3": "BusinessRule_cd20ffa"
          },
          {
            "JI0": "Terrasoft.Core.BusinessRules.BusinessRule",
            "UId": "bd2d4c93-e8ed-049d-7061-22ead5fb9f05",
            "BR1": [
              {
                "JI0": "Terrasoft.Core.BusinessRules.Models.BusinessRuleCase",
                "UId": "d322e776-87f7-65e0-f9cd-ce6bf4e8a040",
                "BRC1": {
                  "JI0": "Terrasoft.Core.BusinessRules.Models.Conditions.BusinessRuleGroupCondition",
                  "UId": "28015109-07a2-0b8b-ebb5-88571eae8ea3",
                  "BGC1": 1,
                  "BGC2": [
                    {
                      "JI0": "Terrasoft.Core.BusinessRules.Models.Conditions.BusinessRuleCondition",
                      "UId": "269b6617-58c9-a549-33dc-6342fbfee155",
                      "BCO1": {
                        "JI0": "Terrasoft.Core.BusinessRules.Models.Expressions.BusinessRuleAttributeExpression",
                        "UId": "4477073f-e3c5-0b7c-3b3b-b604d267462b",
                        "BRE2": "AttributeValue",
                        "BRX1": "UsrCountry",
                        "BRX2": "null"
                      },
                      "BCO3": 1
                    }
                  ]
                },
                "BRC2": [
                  {
                    "JI0": "Terrasoft.Core.BusinessRules.Models.Actions.BusinessRuleActionFilterLookup",
                    "UId": "697e43ee-e941-8522-3662-d34ec99da103",
                    "BRA2": {
                      "JI0": "Terrasoft.Core.BusinessRules.Models.Expressions.BusinessRuleAttributeExpression",
                      "UId": "43073b04-5002-4241-989e-511035af5fc3",
                      "BRX1": "null",
                      "BRX2": "null"
                    },
                    "BRA3": {
                      "JI0": "Terrasoft.Core.BusinessRules.Models.Expressions.BusinessRuleValueExpression",
                      "UId": "7551820c-282e-49fb-8f71-afe7cc1c1526"
                    },
                    "BSFL1": {
                      "JI0": "Terrasoft.Core.BusinessRules.Models.Expressions.BusinessRuleFilterLookupExpression",
                      "UId": "00db6973-953f-d791-15c4-892f859dc973",
                      "BRE1": "Lookup",
                      "BRE3": "City",
                      "BVP1": "UsrCity",
                      "BVF1": "Country"
                    },
                    "BSFR1": {
                      "JI0": "Terrasoft.Core.BusinessRules.Models.Expressions.BusinessRuleFilterLookupExpression",
                      "UId": "ebfe47f9-9965-f0a7-1908-f9daef7fa6a6",
                      "BRE1": "Lookup",
                      "BRE3": "Country",
                      "BVP1": "UsrCountry",
                      "BVF1": "null"
                    }
                  }
                ]
              }
            ],
            "BR2": [
              {
                "JI0": "Terrasoft.Core.BusinessRules.Models.Trigger",
                "UId": "749cbd11-2596-7e5e-5f77-a8b22204341f",
                "BRT2": 2
              },
              {
                "JI0": "Terrasoft.Core.BusinessRules.Models.Trigger",
                "UId": "ae7e6c4d-fa6d-53b8-c386-7443f8c96c04",
                "BRT1": "UsrCountry"
              }
            ],
            "BR3": "BusinessRule_8c12028"
          },
          {
            "JI0": "Terrasoft.Core.BusinessRules.BusinessRule",
            "UId": "18dcb1f0-ccdb-7040-c016-e032c9c25ad2",
            "BR1": [
              {
                "JI0": "Terrasoft.Core.BusinessRules.Models.BusinessRuleCase",
                "UId": "28a3c690-2da9-71a2-f6f4-dae816c32a00",
                "BRC1": {
                  "JI0": "Terrasoft.Core.BusinessRules.Models.Conditions.BusinessRuleCondition",
                  "UId": "5ea17cc3-0f79-8d32-c0cd-bb7f4df00f71",
                  "BCO1": {
                    "JI0": "Terrasoft.Core.BusinessRules.Models.Expressions.BusinessRuleAttributeExpression",
                    "UId": "de2da014-4dd2-857a-a7ec-8a917a48b3e1",
                    "BRE2": "AttributeValue",
                    "BRX1": "UsrCountry"
                  },
                  "BCO2": {
                    "JI0": "Terrasoft.Core.BusinessRules.Models.Expressions.BusinessRuleAttributeExpression",
                    "UId": "b204c254-ce95-ed0c-7de7-68caa23e8d6f",
                    "BRE2": "AttributeValue",
                    "BRX1": "UsrCity.Country"
                  },
                  "BCO3": 3
                },
                "BRC2": [
                  {
                    "JI0": "Terrasoft.Core.BusinessRules.Models.Actions.BusinessRuleActionSetValues",
                    "UId": "dd45a644-b156-e9af-184f-dd892a542172",
                    "BRA2": {
                      "JI0": "Terrasoft.Core.BusinessRules.Models.Expressions.BusinessRuleAttributeExpression",
                      "UId": "fd1b3484-da3f-4a7f-9878-3d2dac03c0bf",
                      "BRX1": "null",
                      "BRX2": "null"
                    },
                    "BRA3": {
                      "JI0": "Terrasoft.Core.BusinessRules.Models.Expressions.BusinessRuleValueExpression",
                      "UId": "67cc1dfd-60d1-42b9-9958-429f787875bd"
                    },
                    "BSVS1": [
                      {
                        "JI0": "Terrasoft.Core.BusinessRules.Models.Expressions.BusinessRuleSetValueItem",
                        "UId": "874376f7-3b29-1388-1eed-602cff8439e6",
                        "BRA2": {
                          "JI0": "Terrasoft.Core.BusinessRules.Models.Expressions.BusinessRuleAttributeExpression",
                          "UId": "7b741eac-2bb0-3a21-a483-414eaf1bbde7",
                          "BRE1": "Lookup",
                          "BRX1": "UsrCity",
                          "BRX2": "null"
                        },
                        "BRA3": {
                          "JI0": "Terrasoft.Core.BusinessRules.Models.Expressions.BusinessRuleEmptyValueExpression",
                          "UId": "e169a78d-187b-e498-b7ae-790fb8e60184",
                          "BRE1": "Lookup",
                          "BVE1": "00000000-0000-0000-0000-000000000000"
                        }
                      }
                    ]
                  }
                ]
              }
            ],
            "BR2": [
              {
                "JI0": "Terrasoft.Core.BusinessRules.Models.Trigger",
                "UId": "1345f3a8-9d6b-9137-2638-36318d37c05d",
                "BRT1": "UsrCountry"
              }
            ],
            "BR3": "Autogenerated_bd2d4c93-e8ed-049d-7061-22ead5fb9f05_ClearValue",
            "BR5": "bd2d4c93-e8ed-049d-7061-22ead5fb9f05",
            "BR6": "697e43ee-e941-8522-3662-d34ec99da103"
          },
          {
            "JI0": "Terrasoft.Core.BusinessRules.BusinessRule",
            "UId": "976d3639-d3f0-0228-d6ec-b40bc2de5d48",
            "BR1": [
              {
                "JI0": "Terrasoft.Core.BusinessRules.Models.BusinessRuleCase",
                "UId": "815e8a6a-85c6-fe7b-f563-87edad1026c3",
                "BRC1": {
                  "JI0": "Terrasoft.Core.BusinessRules.Models.Conditions.BusinessRuleCondition",
                  "UId": "785cd5d8-3130-a6b0-9388-ecbc420bc5de",
                  "BCO1": {
                    "JI0": "Terrasoft.Core.BusinessRules.Models.Expressions.BusinessRuleAttributeExpression",
                    "UId": "8dc04a82-14d1-b063-da5d-fb74e186c3c0",
                    "BRE2": "AttributeValue",
                    "BRX1": "UsrCity"
                  },
                  "BCO3": 1
                },
                "BRC2": [
                  {
                    "JI0": "Terrasoft.Core.BusinessRules.Models.Actions.BusinessRuleActionSetValues",
                    "UId": "a7d70ad0-afd9-1887-bbd7-e85f573bbb1f",
                    "BRA2": {
                      "JI0": "Terrasoft.Core.BusinessRules.Models.Expressions.BusinessRuleAttributeExpression",
                      "UId": "07f375ec-0e2c-450d-bd8a-8f0ee8350ff1",
                      "BRX1": "null",
                      "BRX2": "null"
                    },
                    "BRA3": {
                      "JI0": "Terrasoft.Core.BusinessRules.Models.Expressions.BusinessRuleValueExpression",
                      "UId": "77f6a8d6-077a-4fb2-a908-af831d8ba517"
                    },
                    "BSVS1": [
                      {
                        "JI0": "Terrasoft.Core.BusinessRules.Models.Expressions.BusinessRuleSetValueItem",
                        "UId": "d785d9b6-d6b1-a325-cb63-b4a2899d527f",
                        "BRA2": {
                          "JI0": "Terrasoft.Core.BusinessRules.Models.Expressions.BusinessRuleAttributeExpression",
                          "UId": "c023096f-8f2b-c6f1-2e92-f20c2b010bb1",
                          "BRX1": "UsrCountry",
                          "BRX2": "null"
                        },
                        "BRA3": {
                          "JI0": "Terrasoft.Core.BusinessRules.Models.Expressions.BusinessRuleAttributeExpression",
                          "UId": "13fa0349-e91a-3136-bb14-2a198cf0ac86",
                          "BRE1": "Lookup",
                          "BRE2": "AttributeValue",
                          "BRE3": "Country",
                          "BRX1": "UsrCity.Country"
                        }
                      }
                    ]
                  }
                ]
              }
            ],
            "BR2": [
              {
                "JI0": "Terrasoft.Core.BusinessRules.Models.Trigger",
                "UId": "d12745b0-c44f-d2aa-b593-33d431b1b39b",
                "BRT1": "UsrCity"
              }
            ],
            "BR3": "Autogenerated_bd2d4c93-e8ed-049d-7061-22ead5fb9f05_PopulateValue",
            "BR5": "bd2d4c93-e8ed-049d-7061-22ead5fb9f05",
            "BR6": "697e43ee-e941-8522-3662-d34ec99da103"
          }
        ]
      }
    }
  }
}